gbp/__init__.py
gbp/client.py
gbp/constants.py
gbp/enums.py
gbp/models.py
gbp/payloads.py
gbp/utils.py
clientgbp-1.0.0.dist-info/LICENSE
clientgbp-1.0.0.dist-info/METADATA
clientgbp-1.0.0.dist-info/WHEEL
clientgbp-1.0.0.dist-info/RECORD
