Metadata-Version: 2.3
Name: clientGBP
Version: 1.0.0
Summary: Libreria para el uso de GBP mediante HTTP. Sin utilizar interfaz gráfica (Scraping).Usando las credenciales de una cuenta, se obtiene las cookies de sesión y se pueden realizar operaciones. Se realiza todo de manera sincrona.
License: MIT
Author: Leandro Franco
Author-email: leandro00fr@gmail.com
Requires-Python: >=3.12
Classifier: License :: OSI Approved :: MIT License
Classifier: Programming Language :: Python :: 3
Classifier: Programming Language :: Python :: 3.12
Classifier: Programming Language :: Python :: 3.13
Requires-Dist: beautifulsoup4 (==4.13.5)
Requires-Dist: email-validator (==2.3.0)
Requires-Dist: pydantic-settings (==2.10.1)
Requires-Dist: pydantic[email] (==2.11.9)
Requires-Dist: requests (==2.32.3)
Requires-Dist: requests-toolbelt (==1.0.0)
